{
    "data":[
        {
            "img":"https://cdn.www.egret.com/official/new-egret/img/76x76/egret.jpg",
            "title":"Egret Engine",
            "desc":"Egret Engine 是一款同时支持 TypeScript，JavaScript 和 ES6 语言开发的开源免费 HTML5 2D 引擎。"
        },
        {
            "img": "https://www.egret.com/img/3D/img/logo.png",
            "title": "Egret3D",
            "desc": "性能卓越、包体小巧、采用实体组件系统架构"
        },
        {
            "img": "https://cdn.www.egret.com/official/new-egret/img/76x76/runtime.jpg",
            "title": "Egret Runtime",
            "desc": "Egret Runtime 是由 Egret 发布的致力于提升 HTML5 游戏速度和稳定性的加速器组件。"
        },
        {
            "img": "https://cdn.www.egret.com/official/new-egret/img/76x76/wing.jpg",
            "title": "Egret Wing",
            "desc": "Egret Wing 是一款针对 Egret 项目的 IDE。支持可视化创建、编辑和管理项目 EUI，以及 TS 代码编写和断点调试。"
        },
        {
            "img": "https://cdn.www.egret.com/official/new-egret/img/76x76/dragon-bones.jpg",
            "title": "Egret DragonBones",
            "desc": "DragonBones 是一款开源免费的移动游戏骨骼动画解决方案。"
        },
        {
            "img": "https://cdn.www.egret.com/official/new-egret/img/76x76/lakeshore.jpg",
            "title": "Lakeshore",
            "desc": "Lakeshore 是一款免费无需编程的游戏创作工具，通过Lakeshore可以轻松实现自己的游戏创作梦想。"
        },
        {
            "img": "https://cdn.www.egret.com/official/new-egret/img/76x76/egret.jpg",
            "title": "Egret Engine",
            "desc": "Egret Engine 是一款同时支持 TypeScript，JavaScript 和 ES6 语言开发的开源免费 HTML5 2D 引擎。"
        },
        {
            "img": "https://www.egret.com/img/3D/img/logo.png",
            "title": "Egret3D",
            "desc": "性能卓越、包体小巧、采用实体组件系统架构"
        },
        {
            "img": "https://cdn.www.egret.com/official/new-egret/img/76x76/runtime.jpg",
            "title": "Egret Runtime",
        "desc": "Egret Runtime 是由 Egret 发布的致力于提升 HTML5 游戏速度和稳定性的加速器组件。"
        },
        {
            "img": "https://cdn.www.egret.com/official/new-egret/img/76x76/wing.jpg",
            "title": "Egret Wing",
            "desc": "Egret Wing 是一款针对 Egret 项目的 IDE。支持可视化创建、编辑和管理项目 EUI，以及 TS 代码编写和断点调试。"
        }
    ]
}